NetHawkAnalyzer/__init__.py
NetHawkAnalyzer/analyzer.py
NetHawkAnalyzer/core/__init__.py
NetHawkAnalyzer/core/ai_security_analyzer.py
NetHawkAnalyzer/core/host_scanner.py
NetHawkAnalyzer/core/port_scanner.py
NetHawkAnalyzer/core/service_scanner.py
NetHawkAnalyzer/core/smb_scanner.py
NetHawkAnalyzer/utils/__init__.py
NetHawkAnalyzer/utils/printer.py
NetHawkAnalyzer-0.1.10.dist-info/LICENSE.txt
NetHawkAnalyzer-0.1.10.dist-info/METADATA
NetHawkAnalyzer-0.1.10.dist-info/WHEEL
NetHawkAnalyzer-0.1.10.dist-info/top_level.txt
NetHawkAnalyzer-0.1.10.dist-info/RECORD
