Metadata-Version: 2.1
Name: NetHawkAnalyzer
Version: 0.1.10
Summary: 🔍💻 NetHawkAnalyzer: An advanced AI-powered tool for ethical hacking, cybersecurity network analysis, and vulnerability assessment. 🦅✨
Home-page: https://github.com/sergio11/nethawk_analyzer
Author: Sergio Sánchez Sánchez
Author-email: dreamsoftware92@gmail.com
Keywords: cybersecurity,ethical hacking,network analysis,vulnerability assessment,AI,Scapy,Nmap,Python,information security,security auditing
Classifier: Development Status :: 3 - Alpha
Classifier: Intended Audience :: Developers
Classifier: License :: OSI Approved :: MIT License
Classifier: Programming Language :: Python :: 3
Classifier: Programming Language :: Python :: 3.7
Classifier: Programming Language :: Python :: 3.8
Classifier: Programming Language :: Python :: 3.9
Classifier: Programming Language :: Python :: 3.10
Requires-Python: >=3.7, <4
License-File: LICENSE.txt
Requires-Dist: scapy==2.6.0
Requires-Dist: tqdm==4.65.0
Requires-Dist: rich==13.9.2
Requires-Dist: pysmb==1.2.10
Requires-Dist: python3-nmap==1.9.1
Requires-Dist: langchain==0.2.16
Requires-Dist: langchain-groq==0.1.10
Requires-Dist: fpdf2==2.8.1
